harf_serde/__init__.py
harf_serde/har.py
harf_serde/harf.py
harf_serde/morphism.py
harf_serde/py.typed
harf_serde-1.2b5.dist-info/LICENSE
harf_serde-1.2b5.dist-info/METADATA
harf_serde-1.2b5.dist-info/WHEEL
harf_serde-1.2b5.dist-info/top_level.txt
harf_serde-1.2b5.dist-info/RECORD
