Metadata-Version: 2.1
Name: harf-serde
Version: 1.2b5
Summary: A library of classes for HAR data using pyserde.
Author-email: Brendan <brendandeleeuw@gmail.com>
License: MIT License
Project-URL: Homepage, https://github.com/MystiriodisLykos/har-serde/tree/v1.2b5
Classifier: Programming Language :: Python
Classifier: Programming Language :: Python :: 3
Requires-Python: >=3.8
License-File: LICENSE
Requires-Dist: pyserde
